_plotly_future_
_plotly_utils
attr
attrs
certifi
click
click_plugins
cligj
dateutil
fair-mobil
fiona
geopandas
importlib_metadata
jupyterlab_plotly
numpy
packaging
pandas
plotly
pyproj
pytz
scipy
shapely
tenacity
tzdata
zipp
